emojilib.cpython-35m-darwin.so
emojilib-1.0.1.dist-info/METADATA
emojilib-1.0.1.dist-info/RECORD
emojilib-1.0.1.dist-info/WHEEL
emojilib-1.0.1.dist-info/top_level.txt
